django_collectstatic_bower/__init__.py
django_collectstatic_bower/bower.py
django_collectstatic_bower/staticfiles/__init__.py
django_collectstatic_bower/staticfiles/finders.py
django_collectstatic_bower/tests/__init__.py
django_collectstatic_bower/tests/settings.py
django_collectstatic_bower/tests/test_bower.py
django_collectstatic_bower/tests/test_finder.py
django_collectstatic_bower-0.1.2.dist-info/DESCRIPTION.rst
django_collectstatic_bower-0.1.2.dist-info/METADATA
django_collectstatic_bower-0.1.2.dist-info/RECORD
django_collectstatic_bower-0.1.2.dist-info/WHEEL
django_collectstatic_bower-0.1.2.dist-info/metadata.json
django_collectstatic_bower-0.1.2.dist-info/top_level.txt
