Metadata-Version: 2.0
Name: django-collectstatic-bower
Version: 0.1.2
Summary: Automatically install Bower components using Django's collectstatic
Home-page: https://github.com/nick-allen/django-collectstatic-bower
Author: Nick Allen
Author-email: nick.allen.cse@gmail.com
License: MIT
Platform: UNKNOWN
Requires-Dist: django (>=1.7)
Provides-Extra: test
Requires-Dist: mock; extra == 'test'
Requires-Dist: nose; extra == 'test'
Requires-Dist: tox; extra == 'test'
